jinja_file_renderer/__about__.py
jinja_file_renderer/__init__.py
jinja_file_renderer/cli.py
jinja_file_renderer-0.0.1a0.dist-info/METADATA
jinja_file_renderer-0.0.1a0.dist-info/WHEEL
jinja_file_renderer-0.0.1a0.dist-info/entry_points.txt
jinja_file_renderer-0.0.1a0.dist-info/licenses/LICENSE
jinja_file_renderer-0.0.1a0.dist-info/RECORD
