Metadata-Version: 2.3
Name: jinja-file-renderer
Version: 0.0.1a0
Summary: A tool for copying a directory, during which *.jinja files are rendered via Jinja2.
Project-URL: Documentation, https://jinja-file-renderer.readthedocs.io/
Project-URL: Issues, https://github.com/spranta-devops/jinja-file-renderer/issues
Project-URL: Source, https://github.com/spranta-devops/jinja-file-renderer
Author: Gerd Aschbrenner
License: jinja-file-renderer - A tool for copying a directory, during which *.jinja files are rendered via Jinja2.
License-File: LICENSE
Keywords: jinja,template
Classifier: Development Status :: 4 - Beta
Classifier: Environment :: Console
Classifier: Intended Audience :: Developers
Classifier: License :: OSI Approved :: GNU Affero General Public License v3 or later (AGPLv3+)
Classifier: Natural Language :: English
Classifier: Operating System :: OS Independent
Classifier: Programming Language :: Python :: 3 :: Only
Classifier: Programming Language :: Python :: 3.9
Classifier: Programming Language :: Python :: 3.10
Classifier: Programming Language :: Python :: 3.11
Classifier: Programming Language :: Python :: 3.12
Classifier: Topic :: Software Development :: Code Generators
Classifier: Topic :: Text Processing :: Markup
Classifier: Topic :: Text Processing :: Markup :: HTML
Classifier: Topic :: Text Processing :: Markup :: XML
Classifier: Topic :: Utilities
Classifier: Typing :: Typed
Requires-Python: >=3.9
Requires-Dist: jinja2~=3.1.4
Requires-Dist: python-dotenv~=1.0.1
